{"Fixture":{"Id":718371,"Referee":"Pierre Gaillouste, France","Timezone":"UTC","Date":"2021-08-22T15:00:00+02:00","Timestamp":1629637200,"Periods":{"First":1629637200,"Second":1629640800},"Venue":{"Id":638,"Name":"Stade Matmut-Atlantique","City":"Bordeaux"},"Status":{"Long":"Match Finished","Short":"FT","Elapsed":90}},"League":{"Id":61,"Name":"Ligue 1","Country":"France","Logo":"https://media.api-sports.io/football/leagues/61.png","Flag":"https://media.api-sports.io/flags/fr.svg","Season":2021,"Round":"Regular Season - 3"},"Teams":{"Home":{"Id":78,"Name":"Bordeaux","Logo":"https://media.api-sports.io/football/teams/78.png","Winner":null},"Away":{"Id":77,"Name":"Angers","Logo":"https://media.api-sports.io/football/teams/77.png","Winner":null}},"Goals":{"Home":1,"Away":1},"Score":{"Halftime":{"Home":1,"Away":1},"Fulltime":{"Home":1,"Away":1},"Extratime":{"Home":null,"Away":null},"Penalty":{"Home":null,"Away":null}},"Events":[{"Time":{"Elapsed":10,"Extra":null},"Team":{"Id":78,"Name":"Bordeaux","Logo":"https://media.api-sports.io/football/teams/78.png"},"Player":{"Id":190686,"Name":"S. Mara"},"Assist":{"Id":41324,"Name":"R. Mangas"},"Type":"Goal","Detail":"Normal Goal","Comments":null},{"Time":{"Elapsed":38,"Extra":null},"Team":{"Id":77,"Name":"Angers","Logo":"https://media.api-sports.io/football/teams/77.png"},"Player":{"Id":21144,"Name":"R. Thomas"},"Assist":{"Id":21146,"Name":"A. Fulgini"},"Type":"Goal","Detail":"Normal Goal","Comments":null},{"Time":{"Elapsed":61,"Extra":null},"Team":{"Id":78,"Name":"Bordeaux","Logo":"https://media.api-sports.io/football/teams/78.png"},"Player":{"Id":41324,"Name":"R. Mangas"},"Assist":{"Id":null,"Name":null},"Type":"Card","Detail":"Yellow Card","Comments":"Elbowing"},{"Time":{"Elapsed":63,"Extra":null},"Team":{"Id":78,"Name":"Bordeaux","Logo":"https://media.api-sports.io/football/teams/78.png"},"Player":{"Id":22016,"Name":"R. Oudin"},"Assist":{"Id":162067,"Name":"T. Pembele"},"Type":"subst","Detail":"Substitution 1","Comments":null},{"Time":{"Elapsed":64,"Extra":null},"Team":{"Id":78,"Name":"Bordeaux","Logo":"https://media.api-sports.io/football/teams/78.png"},"Player":{"Id":1265,"Name":"Y. Adli"},"Assist":{"Id":1266,"Name":"T. Basic"},"Type":"subst","Detail":"Substitution 2","Comments":null},{"Time":{"Elapsed":64,"Extra":null},"Team":{"Id":77,"Name":"Angers","Logo":"https://media.api-sports.io/football/teams/77.png"},"Player":{"Id":3407,"Name":"S. Bahoken"},"Assist":{"Id":2710,"Name":"S. Boufal"},"Type":"subst","Detail":"Substitution 1","Comments":null},{"Time":{"Elapsed":74,"Extra":null},"Team":{"Id":78,"Name":"Bordeaux","Logo":"https://media.api-sports.io/football/teams/78.png"},"Player":{"Id":21086,"Name":"E. Kwateng"},"Assist":{"Id":null,"Name":null},"Type":"Card","Detail":"Yellow Card","Comments":"Roughing"},{"Time":{"Elapsed":80,"Extra":null},"Team":{"Id":77,"Name":"Angers","Logo":"https://media.api-sports.io/football/teams/77.png"},"Player":{"Id":129678,"Name":"A. Ounahi"},"Assist":{"Id":21146,"Name":"A. Fulgini"},"Type":"subst","Detail":"Substitution 2","Comments":null},{"Time":{"Elapsed":80,"Extra":null},"Team":{"Id":77,"Name":"Angers","Logo":"https://media.api-sports.io/football/teams/77.png"},"Player":{"Id":21652,"Name":"C. Ninga"},"Assist":{"Id":274312,"Name":"M. Cho"},"Type":"subst","Detail":"Substitution 3","Comments":null},{"Time":{"Elapsed":80,"Extra":null},"Team":{"Id":78,"Name":"Bordeaux","Logo":"https://media.api-sports.io/football/teams/78.png"},"Player":{"Id":2201,"Name":"Mexer"},"Assist":{"Id":1443,"Name":"L. Koscielny"},"Type":"subst","Detail":"Substitution 3","Comments":null},{"Time":{"Elapsed":81,"Extra":null},"Team":{"Id":78,"Name":"Bordeaux","Logo":"https://media.api-sports.io/football/teams/78.png"},"Player":{"Id":1276,"Name":"S. Kalu"},"Assist":{"Id":190686,"Name":"S. Mara"},"Type":"subst","Detail":"Substitution 4","Comments":null},{"Time":{"Elapsed":90,"Extra":null},"Team":{"Id":78,"Name":"Bordeaux","Logo":"https://media.api-sports.io/football/teams/78.png"},"Player":{"Id":1273,"Name":"J. Briand"},"Assist":{"Id":2910,"Name":"Hwang Ui-Jo"},"Type":"subst","Detail":"Substitution 5","Comments":null}],"Lineups":[{"Team":{"Id":78,"Name":"Bordeaux","Logo":"https://media.api-sports.io/football/teams/78.png","Colors":{"Player":{"Primary":"002851","Number":"ffffff","Border":"ff0000"},"Goalkeeper":{"Primary":"ff0000","Number":"ffffff","Border":"ff0000"}}},"Formation":"5-3-2","StartXI":[{"Player":{"Id":1253,"Name":"Beno\u00EEt Costil","Number":1,"Pos":"G","Grid":"1:1"}},{"Player":{"Id":162067,"Name":"Timoth\u00E9e Pembele","Number":22,"Pos":"D","Grid":"2:5"}},{"Player":{"Id":21086,"Name":"Enock Kwateng","Number":25,"Pos":"D","Grid":"2:4"}},{"Player":{"Id":1443,"Name":"Laurent Koscielny","Number":6,"Pos":"D","Grid":"2:3"}},{"Player":{"Id":41324,"Name":"Ricardo Mangas","Number":12,"Pos":"D","Grid":"2:2"}},{"Player":{"Id":7578,"Name":"Gideon Mensah","Number":14,"Pos":"D","Grid":"2:1"}},{"Player":{"Id":206361,"Name":"Issouf Sissokho","Number":20,"Pos":"M","Grid":"3:3"}},{"Player":{"Id":1262,"Name":"Ot\u00E1vio","Number":5,"Pos":"M","Grid":"3:2"}},{"Player":{"Id":1266,"Name":"Toma Ba\u0161i\u0107","Number":26,"Pos":"M","Grid":"3:1"}},{"Player":{"Id":190686,"Name":"S\u00E9kou Mara","Number":11,"Pos":"F","Grid":"4:2"}},{"Player":{"Id":2910,"Name":"Ui-Jo Hwang","Number":18,"Pos":"F","Grid":"4:1"}}],"Substitutes":[{"Player":{"Id":1254,"Name":"Gaetan Poussin","Number":16,"Pos":"G","Grid":null}},{"Player":{"Id":24602,"Name":"Abdel Medioub","Number":3,"Pos":"D","Grid":null}},{"Player":{"Id":2201,"Name":"Edson Mexer","Number":4,"Pos":"D","Grid":null}},{"Player":{"Id":47312,"Name":"Rub\u00E9n Pardo","Number":8,"Pos":"M","Grid":null}},{"Player":{"Id":1276,"Name":"Samuel Kalu","Number":10,"Pos":"F","Grid":null}},{"Player":{"Id":162740,"Name":"Mehdi Zerkane","Number":17,"Pos":"M","Grid":null}},{"Player":{"Id":1265,"Name":"Yacine Adli","Number":19,"Pos":"M","Grid":null}},{"Player":{"Id":22016,"Name":"Remi Oudin","Number":28,"Pos":"F","Grid":null}},{"Player":{"Id":1273,"Name":"Jimmy Briand","Number":7,"Pos":"F","Grid":null}}],"Coach":{"Id":186,"Name":"V. Petkovi\u0107","Photo":"https://media.api-sports.io/football/coachs/186.png"}},{"Team":{"Id":77,"Name":"Angers","Logo":"https://media.api-sports.io/football/teams/77.png","Colors":{"Player":{"Primary":"ffffff","Number":"000000","Border":"669900"},"Goalkeeper":{"Primary":"669900","Number":"ffffff","Border":"669900"}}},"Formation":"3-4-1-2","StartXI":[{"Player":{"Id":21425,"Name":"Paul Bernardoni","Number":1,"Pos":"G","Grid":"1:1"}},{"Player":{"Id":21141,"Name":"Vincent Manceau","Number":29,"Pos":"D","Grid":"2:3"}},{"Player":{"Id":3237,"Name":"Isma\u00EBl Traor\u00E9","Number":8,"Pos":"D","Grid":"2:2"}},{"Player":{"Id":21144,"Name":"Romain Thomas","Number":24,"Pos":"D","Grid":"2:1"}},{"Player":{"Id":20633,"Name":"Jimmy Cabot","Number":11,"Pos":"M","Grid":"3:4"}},{"Player":{"Id":21087,"Name":"Batista Mendy","Number":2,"Pos":"M","Grid":"3:3"}},{"Player":{"Id":21148,"Name":"Thomas Mangani","Number":5,"Pos":"M","Grid":"3:2"}},{"Player":{"Id":2198,"Name":"Souleyman Doumbia","Number":3,"Pos":"M","Grid":"3:1"}},{"Player":{"Id":21146,"Name":"Angelo Fulgini","Number":10,"Pos":"F","Grid":"4:1"}},{"Player":{"Id":274312,"Name":"Mohamed-Ali Cho","Number":21,"Pos":"F","Grid":"5:2"}},{"Player":{"Id":2710,"Name":"Sofiane Boufal","Number":13,"Pos":"F","Grid":"5:1"}}],"Substitutes":[{"Player":{"Id":20622,"Name":"Danijel Petkovi\u0107","Number":30,"Pos":"G","Grid":null}},{"Player":{"Id":3234,"Name":"Abdoulaye Bamba","Number":25,"Pos":"D","Grid":null}},{"Player":{"Id":129678,"Name":"Azzeddine Ounahi","Number":18,"Pos":"M","Grid":null}},{"Player":{"Id":21652,"Name":"Casimir Ninga","Number":9,"Pos":"F","Grid":null}},{"Player":{"Id":20780,"Name":"Mathias Pereira Lage","Number":27,"Pos":"M","Grid":null}},{"Player":{"Id":21145,"Name":"Pierrick Capelle","Number":15,"Pos":"M","Grid":null}},{"Player":{"Id":174659,"Name":"Waniss Taibi","Number":26,"Pos":"M","Grid":null}},{"Player":{"Id":162115,"Name":"Noah Fatar","Number":17,"Pos":"M","Grid":null}},{"Player":{"Id":3407,"Name":"St\u00E9phane Bahoken","Number":19,"Pos":"F","Grid":null}}],"Coach":{"Id":15087,"Name":"G. Baticle","Photo":"https://media.api-sports.io/football/coachs/15087.png"}}],"Statistics":[{"Team":{"Id":78,"Name":"Bordeaux","Logo":"https://media.api-sports.io/football/teams/78.png"},"Statistics":[{"Type":"Shots on Goal","Value":5},{"Type":"Shots off Goal","Value":4},{"Type":"Total Shots","Value":14},{"Type":"Blocked Shots","Value":5},{"Type":"Shots insidebox","Value":5},{"Type":"Shots outsidebox","Value":9},{"Type":"Fouls","Value":19},{"Type":"Corner Kicks","Value":3},{"Type":"Offsides","Value":1},{"Type":"Ball Possession","Value":"53%"},{"Type":"Yellow Cards","Value":2},{"Type":"Red Cards","Value":null},{"Type":"Goalkeeper Saves","Value":2},{"Type":"Total passes","Value":495},{"Type":"Passes accurate","Value":438},{"Type":"Passes %","Value":"88%"}]},{"Team":{"Id":77,"Name":"Angers","Logo":"https://media.api-sports.io/football/teams/77.png"},"Statistics":[{"Type":"Shots on Goal","Value":3},{"Type":"Shots off Goal","Value":3},{"Type":"Total Shots","Value":6},{"Type":"Blocked Shots","Value":null},{"Type":"Shots insidebox","Value":5},{"Type":"Shots outsidebox","Value":1},{"Type":"Fouls","Value":5},{"Type":"Corner Kicks","Value":3},{"Type":"Offsides","Value":1},{"Type":"Ball Possession","Value":"47%"},{"Type":"Yellow Cards","Value":null},{"Type":"Red Cards","Value":null},{"Type":"Goalkeeper Saves","Value":5},{"Type":"Total passes","Value":454},{"Type":"Passes accurate","Value":389},{"Type":"Passes %","Value":"86%"}]}],"Players":[{"Team":{"Id":78,"Name":"Bordeaux","Logo":"https://media.api-sports.io/football/teams/78.png","Update":"2021-08-23T06:06:54+02:00"},"Players":[{"Player":{"Id":1253,"Name":"Beno\u00EEt Costil","Photo":"https://media.api-sports.io/football/players/1253.png"},"Statistics":[{"Games":{"Minutes":93,"Number":1,"Position":"G","Rating":"6.6","Captain":false,"Substitute":false},"Offsides":null,"Shots":{"Total":null,"On":null},"Goals":{"Total":null,"Conceded":1,"Assists":null,"Saves":2},"Passes":{"Total":15,"Key":null,"Accuracy":"11"},"Tackles":{"Total":null,"Blocks":null,"Interceptions":null},"Duels":{"Total":null,"Won":null},"Dribbles":{"Attempts":null,"Success":null,"Past":null},"Fouls":{"Drawn":null,"Committed":null},"Cards":{"Yellow":0,"Red":0},"Penalty":{"Won":null,"Commited":null,"Scored":0,"Missed":0,"Saved":0}}]},{"Player":{"Id":162067,"Name":"Timoth\u00E9e Pembele","Photo":"https://media.api-sports.io/football/players/162067.png"},"Statistics":[{"Games":{"Minutes":63,"Number":22,"Position":"D","Rating":"6.3","Captain":false,"Substitute":false},"Offsides":null,"Shots":{"Total":null,"On":null},"Goals":{"Total":null,"Conceded":0,"Assists":null,"Saves":null},"Passes":{"Total":26,"Key":null,"Accuracy":"20"},"Tackles":{"Total":1,"Blocks":null,"Interceptions":null},"Duels":{"Total":9,"Won":3},"Dribbles":{"Attempts":2,"Success":2,"Past":null},"Fouls":{"Drawn":null,"Committed":3},"Cards":{"Yellow":0,"Red":0},"Penalty":{"Won":null,"Commited":null,"Scored":0,"Missed":0,"Saved":null}}]},{"Player":{"Id":21086,"Name":"Enock Kwateng","Photo":"https://media.api-sports.io/football/players/21086.png"},"Statistics":[{"Games":{"Minutes":93,"Number":25,"Position":"D","Rating":"7.5","Captain":false,"Substitute":false},"Offsides":null,"Shots":{"Total":null,"On":null},"Goals":{"Total":null,"Conceded":0,"Assists":null,"Saves":null},"Passes":{"Total":60,"Key":null,"Accuracy":"54"},"Tackles":{"Total":4,"Blocks":null,"Interceptions":3},"Duels":{"Total":15,"Won":11},"Dribbles":{"Attempts":1,"Success":1,"Past":1},"Fouls":{"Drawn":3,"Committed":2},"Cards":{"Yellow":1,"Red":0},"Penalty":{"Won":null,"Commited":null,"Scored":0,"Missed":0,"Saved":null}}]},{"Player":{"Id":1443,"Name":"Laurent Koscielny","Photo":"https://media.api-sports.io/football/players/1443.png"},"Statistics":[{"Games":{"Minutes":80,"Number":6,"Position":"D","Rating":"7","Captain":true,"Substitute":false},"Offsides":null,"Shots":{"Total":null,"On":null},"Goals":{"Total":null,"Conceded":0,"Assists":null,"Saves":null},"Passes":{"Total":62,"Key":null,"Accuracy":"56"},"Tackles":{"Total":2,"Blocks":null,"Interceptions":1},"Duels":{"Total":7,"Won":4},"Dribbles":{"Attempts":1,"Success":null,"Past":null},"Fouls":{"Drawn":null,"Committed":2},"Cards":{"Yellow":0,"Red":0},"Penalty":{"Won":null,"Commited":null,"Scored":0,"Missed":0,"Saved":null}}]},{"Player":{"Id":41324,"Name":"Ricardo Mangas","Photo":"https://media.api-sports.io/football/players/41324.png"},"Statistics":[{"Games":{"Minutes":93,"Number":12,"Position":"D","Rating":"7","Captain":false,"Substitute":false},"Offsides":null,"Shots":{"Total":null,"On":null},"Goals":{"Total":null,"Conceded":0,"Assists":1,"Saves":null},"Passes":{"Total":55,"Key":2,"Accuracy":"51"},"Tackles":{"Total":3,"Blocks":null,"Interceptions":2},"Duels":{"Total":8,"Won":4},"Dribbles":{"Attempts":2,"Success":null,"Past":null},"Fouls":{"Drawn":null,"Committed":1},"Cards":{"Yellow":1,"Red":0},"Penalty":{"Won":null,"Commited":null,"Scored":0,"Missed":0,"Saved":null}}]},{"Player":{"Id":7578,"Name":"Gideon Mensah","Photo":"https://media.api-sports.io/football/players/7578.png"},"Statistics":[{"Games":{"Minutes":93,"Number":14,"Position":"D","Rating":"6.5","Captain":false,"Substitute":false},"Offsides":1,"Shots":{"Total":null,"On":null},"Goals":{"Total":null,"Conceded":0,"Assists":null,"Saves":null},"Passes":{"Total":44,"Key":null,"Accuracy":"43"},"Tackles":{"Total":5,"Blocks":null,"Interceptions":null},"Duels":{"Total":18,"Won":9},"Dribbles":{"Attempts":4,"Success":2,"Past":3},"Fouls":{"Drawn":1,"Committed":1},"Cards":{"Yellow":0,"Red":0},"Penalty":{"Won":null,"Commited":null,"Scored":0,"Missed":0,"Saved":null}}]},{"Player":{"Id":206361,"Name":"Issouf Sissokho","Photo":"https://media.api-sports.io/football/players/206361.png"},"Statistics":[{"Games":{"Minutes":93,"Number":20,"Position":"M","Rating":"7.3","Captain":false,"Substitute":false},"Offsides":null,"Shots":{"Total":1,"On":1},"Goals":{"Total":null,"Conceded":0,"Assists":null,"Saves":null},"Passes":{"Total":55,"Key":2,"Accuracy":"47"},"Tackles":{"Total":4,"Blocks":null,"Interceptions":1},"Duels":{"Total":8,"Won":5},"Dribbles":{"Attempts":2,"Success":1,"Past":null},"Fouls":{"Drawn":null,"Committed":1},"Cards":{"Yellow":0,"Red":0},"Penalty":{"Won":null,"Commited":null,"Scored":0,"Missed":0,"Saved":null}}]},{"Player":{"Id":1262,"Name":"Ot\u00E1vio","Photo":"https://media.api-sports.io/football/players/1262.png"},"Statistics":[{"Games":{"Minutes":93,"Number":5,"Position":"M","Rating":"7.2","Captain":false,"Substitute":false},"Offsides":null,"Shots":{"Total":2,"On":1},"Goals":{"Total":null,"Conceded":0,"Assists":null,"Saves":null},"Passes":{"Total":63,"Key":1,"Accuracy":"56"},"Tackles":{"Total":7,"Blocks":null,"Interceptions":null},"Duels":{"Total":16,"Won":9},"Dribbles":{"Attempts":1,"Success":1,"Past":3},"Fouls":{"Drawn":null,"Committed":3},"Cards":{"Yellow":0,"Red":0},"Penalty":{"Won":null,"Commited":null,"Scored":0,"Missed":0,"Saved":null}}]},{"Player":{"Id":1266,"Name":"Toma Ba\u0161i\u0107","Photo":"https://media.api-sports.io/football/players/1266.png"},"Statistics":[{"Games":{"Minutes":63,"Number":26,"Position":"M","Rating":"6.3","Captain":false,"Substitute":false},"Offsides":null,"Shots":{"Total":1,"On":null},"Goals":{"Total":null,"Conceded":0,"Assists":null,"Saves":null},"Passes":{"Total":26,"Key":1,"Accuracy":"22"},"Tackles":{"Total":1,"Blocks":null,"Interceptions":1},"Duels":{"Total":6,"Won":1},"Dribbles":{"Attempts":1,"Success":null,"Past":1},"Fouls":{"Drawn":null,"Committed":2},"Cards":{"Yellow":0,"Red":0},"Penalty":{"Won":null,"Commited":null,"Scored":0,"Missed":0,"Saved":null}}]},{"Player":{"Id":190686,"Name":"S\u00E9kou Mara","Photo":"https://media.api-sports.io/football/players/190686.png"},"Statistics":[{"Games":{"Minutes":81,"Number":11,"Position":"F","Rating":"7.2","Captain":false,"Substitute":false},"Offsides":null,"Shots":{"Total":4,"On":3},"Goals":{"Total":1,"Conceded":0,"Assists":null,"Saves":null},"Passes":{"Total":9,"Key":null,"Accuracy":"6"},"Tackles":{"Total":null,"Blocks":null,"Interceptions":null},"Duels":{"Total":13,"Won":3},"Dribbles":{"Attempts":4,"Success":1,"Past":null},"Fouls":{"Drawn":null,"Committed":3},"Cards":{"Yellow":0,"Red":0},"Penalty":{"Won":null,"Commited":null,"Scored":0,"Missed":0,"Saved":null}}]},{"Player":{"Id":2910,"Name":"Ui-Jo Hwang","Photo":"https://media.api-sports.io/football/players/2910.png"},"Statistics":[{"Games":{"Minutes":90,"Number":18,"Position":"F","Rating":"6.7","Captain":false,"Substitute":false},"Offsides":null,"Shots":{"Total":null,"On":null},"Goals":{"Total":null,"Conceded":0,"Assists":null,"Saves":null},"Passes":{"Total":24,"Key":1,"Accuracy":"20"},"Tackles":{"Total":null,"Blocks":null,"Interceptions":null},"Duels":{"Total":6,"Won":1},"Dribbles":{"Attempts":null,"Success":null,"Past":null},"Fouls":{"Drawn":null,"Committed":1},"Cards":{"Yellow":0,"Red":0},"Penalty":{"Won":null,"Commited":null,"Scored":0,"Missed":0,"Saved":null}}]},{"Player":{"Id":1254,"Name":"Gaetan Poussin","Photo":"https://media.api-sports.io/football/players/1254.png"},"Statistics":[{"Games":{"Minutes":null,"Number":16,"Position":"G","Rating":null,"Captain":false,"Substitute":true},"Offsides":null,"Shots":{"Total":null,"On":null},"Goals":{"Total":null,"Conceded":0,"Assists":null,"Saves":null},"Passes":{"Total":null,"Key":null,"Accuracy":null},"Tackles":{"Total":null,"Blocks":null,"Interceptions":null},"Duels":{"Total":null,"Won":null},"Dribbles":{"Attempts":null,"Success":null,"Past":null},"Fouls":{"Drawn":null,"Committed":null},"Cards":{"Yellow":0,"Red":0},"Penalty":{"Won":null,"Commited":null,"Scored":0,"Missed":0,"Saved":null}}]},{"Player":{"Id":24602,"Name":"Abdel Medioub","Photo":"https://media.api-sports.io/football/players/24602.png"},"Statistics":[{"Games":{"Minutes":null,"Number":3,"Position":"D","Rating":null,"Captain":false,"Substitute":true},"Offsides":null,"Shots":{"Total":null,"On":null},"Goals":{"Total":null,"Conceded":0,"Assists":null,"Saves":null},"Passes":{"Total":null,"Key":null,"Accuracy":null},"Tackles":{"Total":null,"Blocks":null,"Interceptions":null},"Duels":{"Total":null,"Won":null},"Dribbles":{"Attempts":null,"Success":null,"Past":null},"Fouls":{"Drawn":null,"Committed":null},"Cards":{"Yellow":0,"Red":0},"Penalty":{"Won":null,"Commited":null,"Scored":0,"Missed":0,"Saved":null}}]},{"Player":{"Id":2201,"Name":"Edson Mexer","Photo":"https://media.api-sports.io/football/players/2201.png"},"Statistics":[{"Games":{"Minutes":13,"Number":4,"Position":"D","Rating":"6.6","Captain":false,"Substitute":true},"Offsides":null,"Shots":{"Total":null,"On":null},"Goals":{"Total":null,"Conceded":0,"Assists":null,"Saves":null},"Passes":{"Total":12,"Key":null,"Accuracy":"11"},"Tackles":{"Total":1,"Blocks":null,"Interceptions":null},"Duels":{"Total":2,"Won":2},"Dribbles":{"Attempts":null,"Success":null,"Past":null},"Fouls":{"Drawn":null,"Committed":null},"Cards":{"Yellow":0,"Red":0},"Penalty":{"Won":null,"Commited":null,"Scored":0,"Missed":0,"Saved":null}}]},{"Player":{"Id":47312,"Name":"Rub\u00E9n Pardo","Photo":"https://media.api-sports.io/football/players/47312.png"},"Statistics":[{"Games":{"Minutes":null,"Number":8,"Position":"M","Rating":null,"Captain":false,"Substitute":true},"Offsides":null,"Shots":{"Total":null,"On":null},"Goals":{"Total":null,"Conceded":0,"Assists":null,"Saves":null},"Passes":{"Total":null,"Key":null,"Accuracy":null},"Tackles":{"Total":null,"Blocks":null,"Interceptions":null},"Duels":{"Total":null,"Won":null},"Dribbles":{"Attempts":null,"Success":null,"Past":null},"Fouls":{"Drawn":null,"Committed":null},"Cards":{"Yellow":0,"Red":0},"Penalty":{"Won":null,"Commited":null,"Scored":0,"Missed":0,"Saved":null}}]},{"Player":{"Id":1276,"Name":"Samuel Kalu","Photo":"https://media.api-sports.io/football/players/1276.png"},"Statistics":[{"Games":{"Minutes":12,"Number":10,"Position":"F","Rating":"6.5","Captain":false,"Substitute":true},"Offsides":null,"Shots":{"Total":null,"On":null},"Goals":{"Total":null,"Conceded":0,"Assists":null,"Saves":null},"Passes":{"Total":2,"Key":null,"Accuracy":"2"},"Tackles":{"Total":null,"Blocks":null,"Interceptions":null},"Duels":{"Total":4,"Won":1},"Dribbles":{"Attempts":2,"Success":1,"Past":null},"Fouls":{"Drawn":null,"Committed":null},"Cards":{"Yellow":0,"Red":0},"Penalty":{"Won":null,"Commited":null,"Scored":0,"Missed":0,"Saved":null}}]},{"Player":{"Id":162740,"Name":"Mehdi Zerkane","Photo":"https://media.api-sports.io/football/players/162740.png"},"Statistics":[{"Games":{"Minutes":null,"Number":17,"Position":"M","Rating":null,"Captain":false,"Substitute":true},"Offsides":null,"Shots":{"Total":null,"On":null},"Goals":{"Total":null,"Conceded":0,"Assists":null,"Saves":null},"Passes":{"Total":null,"Key":null,"Accuracy":null},"Tackles":{"Total":null,"Blocks":null,"Interceptions":null},"Duels":{"Total":null,"Won":null},"Dribbles":{"Attempts":null,"Success":null,"Past":null},"Fouls":{"Drawn":null,"Committed":null},"Cards":{"Yellow":0,"Red":0},"Penalty":{"Won":null,"Commited":null,"Scored":0,"Missed":0,"Saved":null}}]},{"Player":{"Id":1265,"Name":"Yacine Adli","Photo":"https://media.api-sports.io/football/players/1265.png"},"Statistics":[{"Games":{"Minutes":30,"Number":19,"Position":"M","Rating":"6.6","Captain":false,"Substitute":true},"Offsides":null,"Shots":{"Total":null,"On":null},"Goals":{"Total":null,"Conceded":0,"Assists":null,"Saves":null},"Passes":{"Total":19,"Key":2,"Accuracy":"18"},"Tackles":{"Total":null,"Blocks":null,"Interceptions":null},"Duels":{"Total":3,"Won":null},"Dribbles":{"Attempts":null,"Success":null,"Past":null},"Fouls":{"Drawn":null,"Committed":null},"Cards":{"Yellow":0,"Red":0},"Penalty":{"Won":null,"Commited":null,"Scored":0,"Missed":0,"Saved":null}}]},{"Player":{"Id":22016,"Name":"Remi Oudin","Photo":"https://media.api-sports.io/football/players/22016.png"},"Statistics":[{"Games":{"Minutes":30,"Number":28,"Position":"F","Rating":"6.9","Captain":false,"Substitute":true},"Offsides":null,"Shots":{"Total":1,"On":null},"Goals":{"Total":null,"Conceded":0,"Assists":null,"Saves":null},"Passes":{"Total":21,"Key":2,"Accuracy":"19"},"Tackles":{"Total":null,"Blocks":null,"Interceptions":null},"Duels":{"Total":1,"Won":null},"Dribbles":{"Attempts":1,"Success":null,"Past":null},"Fouls":{"Drawn":null,"Committed":null},"Cards":{"Yellow":0,"Red":0},"Penalty":{"Won":null,"Commited":null,"Scored":0,"Missed":0,"Saved":null}}]},{"Player":{"Id":1273,"Name":"Jimmy Briand","Photo":"https://media.api-sports.io/football/players/1273.png"},"Statistics":[{"Games":{"Minutes":3,"Number":7,"Position":"F","Rating":null,"Captain":false,"Substitute":true},"Offsides":null,"Shots":{"Total":null,"On":null},"Goals":{"Total":null,"Conceded":0,"Assists":null,"Saves":null},"Passes":{"Total":2,"Key":null,"Accuracy":"2"},"Tackles":{"Total":null,"Blocks":null,"Interceptions":null},"Duels":{"Total":null,"Won":null},"Dribbles":{"Attempts":null,"Success":null,"Past":null},"Fouls":{"Drawn":null,"Committed":null},"Cards":{"Yellow":0,"Red":0},"Penalty":{"Won":null,"Commited":null,"Scored":0,"Missed":0,"Saved":null}}]}]},{"Team":{"Id":77,"Name":"Angers","Logo":"https://media.api-sports.io/football/teams/77.png","Update":"2021-08-23T06:06:54+02:00"},"Players":[{"Player":{"Id":21425,"Name":"Paul Bernardoni","Photo":"https://media.api-sports.io/football/players/21425.png"},"Statistics":[{"Games":{"Minutes":93,"Number":1,"Position":"G","Rating":"7.3","Captain":false,"Substitute":false},"Offsides":null,"Shots":{"Total":null,"On":null},"Goals":{"Total":null,"Conceded":1,"Assists":null,"Saves":5},"Passes":{"Total":16,"Key":null,"Accuracy":"10"},"Tackles":{"Total":null,"Blocks":null,"Interceptions":null},"Duels":{"Total":null,"Won":null},"Dribbles":{"Attempts":null,"Success":null,"Past":null},"Fouls":{"Drawn":null,"Committed":null},"Cards":{"Yellow":0,"Red":0},"Penalty":{"Won":null,"Commited":null,"Scored":0,"Missed":0,"Saved":0}}]},{"Player":{"Id":21141,"Name":"Vincent Manceau","Photo":"https://media.api-sports.io/football/players/21141.png"},"Statistics":[{"Games":{"Minutes":93,"Number":29,"Position":"D","Rating":"7.2","Captain":false,"Substitute":false},"Offsides":null,"Shots":{"Total":null,"On":null},"Goals":{"Total":null,"Conceded":0,"Assists":null,"Saves":null},"Passes":{"Total":63,"Key":null,"Accuracy":"60"},"Tackles":{"Total":1,"Blocks":null,"Interceptions":3},"Duels":{"Total":3,"Won":3},"Dribbles":{"Attempts":null,"Success":null,"Past":null},"Fouls":{"Drawn":1,"Committed":null},"Cards":{"Yellow":0,"Red":0},"Penalty":{"Won":null,"Commited":null,"Scored":0,"Missed":0,"Saved":null}}]},{"Player":{"Id":3237,"Name":"Isma\u00EBl Traor\u00E9","Photo":"https://media.api-sports.io/football/players/3237.png"},"Statistics":[{"Games":{"Minutes":93,"Number":8,"Position":"D","Rating":"6.9","Captain":true,"Substitute":false},"Offsides":null,"Shots":{"Total":null,"On":null},"Goals":{"Total":null,"Conceded":0,"Assists":null,"Saves":null},"Passes":{"Total":51,"Key":null,"Accuracy":"46"},"Tackles":{"Total":1,"Blocks":null,"Interceptions":1},"Duels":{"Total":2,"Won":1},"Dribbles":{"Attempts":null,"Success":null,"Past":1},"Fouls":{"Drawn":null,"Committed":null},"Cards":{"Yellow":0,"Red":0},"Penalty":{"Won":null,"Commited":null,"Scored":0,"Missed":0,"Saved":null}}]},{"Player":{"Id":21144,"Name":"Romain Thomas","Photo":"https://media.api-sports.io/football/players/21144.png"},"Statistics":[{"Games":{"Minutes":93,"Number":24,"Position":"D","Rating":"8.3","Captain":false,"Substitute":false},"Offsides":null,"Shots":{"Total":2,"On":2},"Goals":{"Total":1,"Conceded":0,"Assists":null,"Saves":null},"Passes":{"Total":57,"Key":null,"Accuracy":"51"},"Tackles":{"Total":3,"Blocks":null,"Interceptions":2},"Duels":{"Total":10,"Won":6},"Dribbles":{"Attempts":null,"Success":null,"Past":1},"Fouls":{"Drawn":1,"Committed":1},"Cards":{"Yellow":0,"Red":0},"Penalty":{"Won":null,"Commited":null,"Scored":0,"Missed":0,"Saved":null}}]},{"Player":{"Id":20633,"Name":"Jimmy Cabot","Photo":"https://media.api-sports.io/football/players/20633.png"},"Statistics":[{"Games":{"Minutes":93,"Number":11,"Position":"M","Rating":"7.2","Captain":false,"Substitute":false},"Offsides":null,"Shots":{"Total":null,"On":null},"Goals":{"Total":null,"Conceded":0,"Assists":null,"Saves":null},"Passes":{"Total":46,"Key":3,"Accuracy":"39"},"Tackles":{"Total":6,"Blocks":null,"Interceptions":null},"Duels":{"Total":20,"Won":11},"Dribbles":{"Attempts":3,"Success":2,"Past":2},"Fouls":{"Drawn":2,"Committed":null},"Cards":{"Yellow":0,"Red":0},"Penalty":{"Won":null,"Commited":null,"Scored":0,"Missed":0,"Saved":null}}]},{"Player":{"Id":21087,"Name":"Batista Mendy","Photo":"https://media.api-sports.io/football/players/21087.png"},"Statistics":[{"Games":{"Minutes":93,"Number":2,"Position":"M","Rating":"6.9","Captain":false,"Substitute":false},"Offsides":null,"Shots":{"Total":null,"On":null},"Goals":{"Total":null,"Conceded":0,"Assists":null,"Saves":null},"Passes":{"Total":32,"Key":null,"Accuracy":"29"},"Tackles":{"Total":3,"Blocks":null,"Interceptions":1},"Duels":{"Total":5,"Won":3},"Dribbles":{"Attempts":null,"Success":null,"Past":2},"Fouls":{"Drawn":null,"Committed":null},"Cards":{"Yellow":0,"Red":0},"Penalty":{"Won":null,"Commited":null,"Scored":0,"Missed":0,"Saved":null}}]},{"Player":{"Id":21148,"Name":"Thomas Mangani","Photo":"https://media.api-sports.io/football/players/21148.png"},"Statistics":[{"Games":{"Minutes":93,"Number":5,"Position":"M","Rating":"7.3","Captain":false,"Substitute":false},"Offsides":null,"Shots":{"Total":1,"On":null},"Goals":{"Total":null,"Conceded":0,"Assists":null,"Saves":null},"Passes":{"Total":64,"Key":null,"Accuracy":"52"},"Tackles":{"Total":5,"Blocks":null,"Interceptions":3},"Duels":{"Total":9,"Won":7},"Dribbles":{"Attempts":null,"Success":null,"Past":1},"Fouls":{"Drawn":1,"Committed":null},"Cards":{"Yellow":0,"Red":0},"Penalty":{"Won":null,"Commited":null,"Scored":0,"Missed":0,"Saved":null}}]},{"Player":{"Id":2198,"Name":"Souleyman Doumbia","Photo":"https://media.api-sports.io/football/players/2198.png"},"Statistics":[{"Games":{"Minutes":93,"Number":3,"Position":"M","Rating":"7.2","Captain":false,"Substitute":false},"Offsides":null,"Shots":{"Total":null,"On":null},"Goals":{"Total":null,"Conceded":0,"Assists":null,"Saves":null},"Passes":{"Total":46,"Key":null,"Accuracy":"39"},"Tackles":{"Total":2,"Blocks":null,"Interceptions":2},"Duels":{"Total":7,"Won":6},"Dribbles":{"Attempts":null,"Success":null,"Past":null},"Fouls":{"Drawn":2,"Committed":null},"Cards":{"Yellow":0,"Red":0},"Penalty":{"Won":null,"Commited":null,"Scored":0,"Missed":0,"Saved":null}}]},{"Player":{"Id":21146,"Name":"Angelo Fulgini","Photo":"https://media.api-sports.io/football/players/21146.png"},"Statistics":[{"Games":{"Minutes":80,"Number":10,"Position":"F","Rating":"6.9","Captain":false,"Substitute":false},"Offsides":null,"Shots":{"Total":1,"On":null},"Goals":{"Total":null,"Conceded":0,"Assists":1,"Saves":null},"Passes":{"Total":33,"Key":1,"Accuracy":"29"},"Tackles":{"Total":1,"Blocks":null,"Interceptions":null},"Duels":{"Total":17,"Won":9},"Dribbles":{"Attempts":5,"Success":1,"Past":1},"Fouls":{"Drawn":5,"Committed":null},"Cards":{"Yellow":0,"Red":0},"Penalty":{"Won":null,"Commited":null,"Scored":0,"Missed":0,"Saved":null}}]},{"Player":{"Id":274312,"Name":"Mohamed-Ali Cho","Photo":"https://media.api-sports.io/football/players/274312.png"},"Statistics":[{"Games":{"Minutes":80,"Number":21,"Position":"F","Rating":"6.5","Captain":false,"Substitute":false},"Offsides":1,"Shots":{"Total":1,"On":1},"Goals":{"Total":null,"Conceded":0,"Assists":null,"Saves":null},"Passes":{"Total":15,"Key":null,"Accuracy":"10"},"Tackles":{"Total":1,"Blocks":null,"Interceptions":null},"Duels":{"Total":15,"Won":6},"Dribbles":{"Attempts":6,"Success":3,"Past":null},"Fouls":{"Drawn":1,"Committed":null},"Cards":{"Yellow":0,"Red":0},"Penalty":{"Won":null,"Commited":null,"Scored":0,"Missed":0,"Saved":null}}]},{"Player":{"Id":2710,"Name":"Sofiane Boufal","Photo":"https://media.api-sports.io/football/players/2710.png"},"Statistics":[{"Games":{"Minutes":64,"Number":13,"Position":"F","Rating":"6.9","Captain":false,"Substitute":false},"Offsides":null,"Shots":{"Total":1,"On":null},"Goals":{"Total":null,"Conceded":0,"Assists":null,"Saves":null},"Passes":{"Total":24,"Key":1,"Accuracy":"18"},"Tackles":{"Total":1,"Blocks":null,"Interceptions":null},"Duels":{"Total":16,"Won":8},"Dribbles":{"Attempts":4,"Success":1,"Past":1},"Fouls":{"Drawn":6,"Committed":null},"Cards":{"Yellow":0,"Red":0},"Penalty":{"Won":null,"Commited":null,"Scored":0,"Missed":0,"Saved":null}}]},{"Player":{"Id":20622,"Name":"Danijel Petkovi\u0107","Photo":"https://media.api-sports.io/football/players/20622.png"},"Statistics":[{"Games":{"Minutes":null,"Number":30,"Position":"G","Rating":null,"Captain":false,"Substitute":true},"Offsides":null,"Shots":{"Total":null,"On":null},"Goals":{"Total":null,"Conceded":0,"Assists":null,"Saves":null},"Passes":{"Total":null,"Key":null,"Accuracy":null},"Tackles":{"Total":null,"Blocks":null,"Interceptions":null},"Duels":{"Total":null,"Won":null},"Dribbles":{"Attempts":null,"Success":null,"Past":null},"Fouls":{"Drawn":null,"Committed":null},"Cards":{"Yellow":0,"Red":0},"Penalty":{"Won":null,"Commited":null,"Scored":0,"Missed":0,"Saved":null}}]},{"Player":{"Id":3234,"Name":"Abdoulaye Bamba","Photo":"https://media.api-sports.io/football/players/3234.png"},"Statistics":[{"Games":{"Minutes":null,"Number":25,"Position":"D","Rating":null,"Captain":false,"Substitute":true},"Offsides":null,"Shots":{"Total":null,"On":null},"Goals":{"Total":null,"Conceded":0,"Assists":null,"Saves":null},"Passes":{"Total":null,"Key":null,"Accuracy":null},"Tackles":{"Total":null,"Blocks":null,"Interceptions":null},"Duels":{"Total":null,"Won":null},"Dribbles":{"Attempts":null,"Success":null,"Past":null},"Fouls":{"Drawn":null,"Committed":null},"Cards":{"Yellow":0,"Red":0},"Penalty":{"Won":null,"Commited":null,"Scored":0,"Missed":0,"Saved":null}}]},{"Player":{"Id":129678,"Name":"Azzeddine Ounahi","Photo":"https://media.api-sports.io/football/players/129678.png"},"Statistics":[{"Games":{"Minutes":13,"Number":18,"Position":"M","Rating":"6.5","Captain":false,"Substitute":true},"Offsides":null,"Shots":{"Total":null,"On":null},"Goals":{"Total":null,"Conceded":0,"Assists":null,"Saves":null},"Passes":{"Total":5,"Key":null,"Accuracy":"5"},"Tackles":{"Total":1,"Blocks":null,"Interceptions":null},"Duels":{"Total":5,"Won":2},"Dribbles":{"Attempts":2,"Success":1,"Past":1},"Fouls":{"Drawn":null,"Committed":1},"Cards":{"Yellow":0,"Red":0},"Penalty":{"Won":null,"Commited":null,"Scored":0,"Missed":0,"Saved":null}}]},{"Player":{"Id":21652,"Name":"Casimir Ninga","Photo":"https://media.api-sports.io/football/players/21652.png"},"Statistics":[{"Games":{"Minutes":13,"Number":9,"Position":"F","Rating":"6.2","Captain":false,"Substitute":true},"Offsides":null,"Shots":{"Total":null,"On":null},"Goals":{"Total":null,"Conceded":0,"Assists":null,"Saves":null},"Passes":{"Total":null,"Key":null,"Accuracy":null},"Tackles":{"Total":1,"Blocks":null,"Interceptions":null},"Duels":{"Total":5,"Won":1},"Dribbles":{"Attempts":1,"Success":null,"Past":null},"Fouls":{"Drawn":null,"Committed":3},"Cards":{"Yellow":0,"Red":0},"Penalty":{"Won":null,"Commited":null,"Scored":0,"Missed":0,"Saved":null}}]},{"Player":{"Id":20780,"Name":"Mathias Pereira Lage","Photo":"https://media.api-sports.io/football/players/20780.png"},"Statistics":[{"Games":{"Minutes":null,"Number":27,"Position":"M","Rating":null,"Captain":false,"Substitute":true},"Offsides":null,"Shots":{"Total":null,"On":null},"Goals":{"Total":null,"Conceded":0,"Assists":null,"Saves":null},"Passes":{"Total":null,"Key":null,"Accuracy":null},"Tackles":{"Total":null,"Blocks":null,"Interceptions":null},"Duels":{"Total":null,"Won":null},"Dribbles":{"Attempts":null,"Success":null,"Past":null},"Fouls":{"Drawn":null,"Committed":null},"Cards":{"Yellow":0,"Red":0},"Penalty":{"Won":null,"Commited":null,"Scored":0,"Missed":0,"Saved":null}}]},{"Player":{"Id":21145,"Name":"Pierrick Capelle","Photo":"https://media.api-sports.io/football/players/21145.png"},"Statistics":[{"Games":{"Minutes":null,"Number":15,"Position":"M","Rating":null,"Captain":false,"Substitute":true},"Offsides":null,"Shots":{"Total":null,"On":null},"Goals":{"Total":null,"Conceded":0,"Assists":null,"Saves":null},"Passes":{"Total":null,"Key":null,"Accuracy":null},"Tackles":{"Total":null,"Blocks":null,"Interceptions":null},"Duels":{"Total":null,"Won":null},"Dribbles":{"Attempts":null,"Success":null,"Past":null},"Fouls":{"Drawn":null,"Committed":null},"Cards":{"Yellow":0,"Red":0},"Penalty":{"Won":null,"Commited":null,"Scored":0,"Missed":0,"Saved":null}}]},{"Player":{"Id":174659,"Name":"Waniss Taibi","Photo":"https://media.api-sports.io/football/players/174659.png"},"Statistics":[{"Games":{"Minutes":null,"Number":26,"Position":"M","Rating":null,"Captain":false,"Substitute":true},"Offsides":null,"Shots":{"Total":null,"On":null},"Goals":{"Total":null,"Conceded":0,"Assists":null,"Saves":null},"Passes":{"Total":null,"Key":null,"Accuracy":null},"Tackles":{"Total":null,"Blocks":null,"Interceptions":null},"Duels":{"Total":null,"Won":null},"Dribbles":{"Attempts":null,"Success":null,"Past":null},"Fouls":{"Drawn":null,"Committed":null},"Cards":{"Yellow":0,"Red":0},"Penalty":{"Won":null,"Commited":null,"Scored":0,"Missed":0,"Saved":null}}]},{"Player":{"Id":162115,"Name":"Noah Fatar","Photo":"https://media.api-sports.io/football/players/162115.png"},"Statistics":[{"Games":{"Minutes":null,"Number":17,"Position":"M","Rating":null,"Captain":false,"Substitute":true},"Offsides":null,"Shots":{"Total":null,"On":null},"Goals":{"Total":null,"Conceded":0,"Assists":null,"Saves":null},"Passes":{"Total":null,"Key":null,"Accuracy":null},"Tackles":{"Total":null,"Blocks":null,"Interceptions":null},"Duels":{"Total":null,"Won":null},"Dribbles":{"Attempts":null,"Success":null,"Past":null},"Fouls":{"Drawn":null,"Committed":null},"Cards":{"Yellow":0,"Red":0},"Penalty":{"Won":null,"Commited":null,"Scored":0,"Missed":0,"Saved":null}}]},{"Player":{"Id":3407,"Name":"St\u00E9phane Bahoken","Photo":"https://media.api-sports.io/football/players/3407.png"},"Statistics":[{"Games":{"Minutes":29,"Number":19,"Position":"F","Rating":"6.5","Captain":false,"Substitute":true},"Offsides":null,"Shots":{"Total":null,"On":null},"Goals":{"Total":null,"Conceded":0,"Assists":null,"Saves":null},"Passes":{"Total":2,"Key":null,"Accuracy":"1"},"Tackles":{"Total":null,"Blocks":null,"Interceptions":null},"Duels":{"Total":3,"Won":null},"Dribbles":{"Attempts":1,"Success":null,"Past":null},"Fouls":{"Drawn":null,"Committed":null},"Cards":{"Yellow":0,"Red":0},"Penalty":{"Won":null,"Commited":null,"Scored":0,"Missed":0,"Saved":null}}]}]}]}