{"get":"players","parameters":{"team":"95","season":"2021"},"errors":[],"results":20,"paging":{"current":1,"total":2},"response":[{"player":{"id":22246,"name":"L. Kon\u00E9","firstname":"Lamine","lastname":"Kon\u00E9","age":32,"birth":{"date":"1989-02-01","place":"Paris","country":"France"},"nationality":"C\u00F4te d\u0027Ivoire","height":"189 cm","weight":"90 kg","injured":false,"photo":"https://media.api-sports.io/football/players/22246.png"},"statistics":[{"team":{"id":95,"name":"Strasbourg","logo":"https://media.api-sports.io/football/teams/95.png"},"league":{"id":61,"name":"Ligue 1","country":"France","logo":"https://media.api-sports.io/football/leagues/61.png","flag":"https://media.api-sports.io/flags/fr.svg","season":2021},"games":{"appearences":null,"lineups":null,"minutes":null,"number":null,"position":"Defender","rating":null,"captain":false},"substitutes":{"_in":0,"_out":0,"bench":null},"shots":{"total":null,"on":null},"goals":{"total":null,"conceded":null,"assists":null,"saves":null},"passes":{"total":null,"key":null,"accuracy":null},"tackles":{"total":null,"blocks":null,"interceptions":null},"duels":{"total":null,"won":null},"dribbles":{"attempts":null,"success":null,"past":null},"fouls":{"drawn":null,"committed":null},"cards":{"yellow":null,"yellowred":null,"red":null},"penalty":{"won":null,"commited":null,"scored":null,"missed":null,"saved":null}}]},{"player":{"id":284796,"name":"M. Elimbi Gilbert","firstname":"Marvin","lastname":"Elimbi Gilbert","age":18,"birth":{"date":"2003-02-20","place":null,"country":"France"},"nationality":"France","height":null,"weight":null,"injured":false,"photo":"https://media.api-sports.io/football/players/284796.png"},"statistics":[{"team":{"id":95,"name":"Strasbourg","logo":"https://media.api-sports.io/football/teams/95.png"},"league":{"id":61,"name":"Ligue 1","country":"France","logo":"https://media.api-sports.io/football/leagues/61.png","flag":"https://media.api-sports.io/flags/fr.svg","season":2021},"games":{"appearences":null,"lineups":null,"minutes":null,"number":null,"position":"Defender","rating":null,"captain":false},"substitutes":{"_in":0,"_out":0,"bench":null},"shots":{"total":null,"on":null},"goals":{"total":null,"conceded":null,"assists":null,"saves":null},"passes":{"total":null,"key":null,"accuracy":null},"tackles":{"total":null,"blocks":null,"interceptions":null},"duels":{"total":null,"won":null},"dribbles":{"attempts":null,"success":null,"past":null},"fouls":{"drawn":null,"committed":null},"cards":{"yellow":null,"yellowred":null,"red":null},"penalty":{"won":null,"commited":null,"scored":null,"missed":null,"saved":null}}]},{"player":{"id":191170,"name":"B. Besic","firstname":"Benjamin","lastname":"Besic","age":19,"birth":{"date":"2002-06-02","place":"Colmar","country":"France"},"nationality":"France","height":"180 cm","weight":"77 kg","injured":false,"photo":"https://media.api-sports.io/football/players/191170.png"},"statistics":[{"team":{"id":95,"name":"Strasbourg","logo":"https://media.api-sports.io/football/teams/95.png"},"league":{"id":61,"name":"Ligue 1","country":"France","logo":"https://media.api-sports.io/football/leagues/61.png","flag":"https://media.api-sports.io/flags/fr.svg","season":2021},"games":{"appearences":null,"lineups":null,"minutes":null,"number":null,"position":"Midfielder","rating":null,"captain":false},"substitutes":{"_in":0,"_out":0,"bench":null},"shots":{"total":null,"on":null},"goals":{"total":null,"conceded":null,"assists":null,"saves":null},"passes":{"total":null,"key":null,"accuracy":null},"tackles":{"total":null,"blocks":null,"interceptions":null},"duels":{"total":null,"won":null},"dribbles":{"attempts":null,"success":null,"past":null},"fouls":{"drawn":null,"committed":null},"cards":{"yellow":null,"yellowred":null,"red":null},"penalty":{"won":null,"commited":null,"scored":null,"missed":null,"saved":null}}]},{"player":{"id":191199,"name":"N. Sommer","firstname":"No\u00E9","lastname":"Sommer","age":20,"birth":{"date":"2001-06-17","place":"Mulhouse","country":"France"},"nationality":"France","height":null,"weight":null,"injured":false,"photo":"https://media.api-sports.io/football/players/191199.png"},"statistics":[{"team":{"id":95,"name":"Strasbourg","logo":"https://media.api-sports.io/football/teams/95.png"},"league":{"id":61,"name":"Ligue 1","country":"France","logo":"https://media.api-sports.io/football/leagues/61.png","flag":"https://media.api-sports.io/flags/fr.svg","season":2021},"games":{"appearences":null,"lineups":null,"minutes":null,"number":null,"position":"Midfielder","rating":null,"captain":false},"substitutes":{"_in":0,"_out":0,"bench":null},"shots":{"total":null,"on":null},"goals":{"total":null,"conceded":null,"assists":null,"saves":null},"passes":{"total":null,"key":null,"accuracy":null},"tackles":{"total":null,"blocks":null,"interceptions":null},"duels":{"total":null,"won":null},"dribbles":{"attempts":null,"success":null,"past":null},"fouls":{"drawn":null,"committed":null},"cards":{"yellow":null,"yellowred":null,"red":null},"penalty":{"won":null,"commited":null,"scored":null,"missed":null,"saved":null}}]},{"player":{"id":128990,"name":"A. Ousmane","firstname":"Abdoulaye","lastname":"Ousmane","age":21,"birth":{"date":"2000-02-22","place":"Maubeuge","country":"France"},"nationality":"Mauritania","height":"183 cm","weight":null,"injured":false,"photo":"https://media.api-sports.io/football/players/128990.png"},"statistics":[{"team":{"id":95,"name":"Strasbourg","logo":"https://media.api-sports.io/football/teams/95.png"},"league":{"id":61,"name":"Ligue 1","country":"France","logo":"https://media.api-sports.io/football/leagues/61.png","flag":"https://media.api-sports.io/flags/fr.svg","season":2021},"games":{"appearences":null,"lineups":null,"minutes":null,"number":null,"position":"Defender","rating":null,"captain":false},"substitutes":{"_in":0,"_out":0,"bench":null},"shots":{"total":null,"on":null},"goals":{"total":null,"conceded":null,"assists":null,"saves":null},"passes":{"total":null,"key":null,"accuracy":null},"tackles":{"total":null,"blocks":null,"interceptions":null},"duels":{"total":null,"won":null},"dribbles":{"attempts":null,"success":null,"past":null},"fouls":{"drawn":null,"committed":null},"cards":{"yellow":null,"yellowred":null,"red":null},"penalty":{"won":null,"commited":null,"scored":null,"missed":null,"saved":null}}]},{"player":{"id":2919,"name":"M. Sels","firstname":"Matz","lastname":"Sels","age":29,"birth":{"date":"1992-02-26","place":"Duffel","country":"Belgium"},"nationality":"Belgium","height":"188 cm","weight":"75 kg","injured":false,"photo":"https://media.api-sports.io/football/players/2919.png"},"statistics":[{"team":{"id":95,"name":"Strasbourg","logo":"https://media.api-sports.io/football/teams/95.png"},"league":{"id":61,"name":"Ligue 1","country":"France","logo":"https://media.api-sports.io/football/leagues/61.png","flag":"https://media.api-sports.io/flags/fr.svg","season":2021},"games":{"appearences":2,"lineups":2,"minutes":180,"number":null,"position":"Goalkeeper","rating":"5.850000","captain":false},"substitutes":{"_in":0,"_out":0,"bench":0},"shots":{"total":null,"on":null},"goals":{"total":0,"conceded":6,"assists":null,"saves":2},"passes":{"total":44,"key":null,"accuracy":13},"tackles":{"total":null,"blocks":null,"interceptions":null},"duels":{"total":1,"won":1},"dribbles":{"attempts":null,"success":null,"past":null},"fouls":{"drawn":null,"committed":null},"cards":{"yellow":0,"yellowred":0,"red":0},"penalty":{"won":null,"commited":null,"scored":0,"missed":0,"saved":0}}]},{"player":{"id":22242,"name":"E. Kawashima","firstname":"Eiji","lastname":"Kawashima","age":38,"birth":{"date":"1983-03-20","place":"Yono","country":"Japan"},"nationality":"Japan","height":"185 cm","weight":"74 kg","injured":false,"photo":"https://media.api-sports.io/football/players/22242.png"},"statistics":[{"team":{"id":95,"name":"Strasbourg","logo":"https://media.api-sports.io/football/teams/95.png"},"league":{"id":61,"name":"Ligue 1","country":"France","logo":"https://media.api-sports.io/football/leagues/61.png","flag":"https://media.api-sports.io/flags/fr.svg","season":2021},"games":{"appearences":0,"lineups":0,"minutes":0,"number":null,"position":"Goalkeeper","rating":null,"captain":false},"substitutes":{"_in":0,"_out":0,"bench":2},"shots":{"total":null,"on":null},"goals":{"total":0,"conceded":0,"assists":null,"saves":null},"passes":{"total":null,"key":null,"accuracy":null},"tackles":{"total":null,"blocks":null,"interceptions":null},"duels":{"total":null,"won":null},"dribbles":{"attempts":null,"success":null,"past":null},"fouls":{"drawn":null,"committed":null},"cards":{"yellow":0,"yellowred":0,"red":0},"penalty":{"won":null,"commited":null,"scored":0,"missed":0,"saved":0}}]},{"player":{"id":22241,"name":"B. Kamara","firstname":"Bingourou","lastname":"Kamara","age":25,"birth":{"date":"1996-10-21","place":"Longjumeau","country":"France"},"nationality":"Senegal","height":"196 cm","weight":"92 kg","injured":false,"photo":"https://media.api-sports.io/football/players/22241.png"},"statistics":[{"team":{"id":95,"name":"Strasbourg","logo":"https://media.api-sports.io/football/teams/95.png"},"league":{"id":61,"name":"Ligue 1","country":"France","logo":"https://media.api-sports.io/football/leagues/61.png","flag":"https://media.api-sports.io/flags/fr.svg","season":2021},"games":{"appearences":0,"lineups":0,"minutes":0,"number":null,"position":"Goalkeeper","rating":null,"captain":false},"substitutes":{"_in":0,"_out":0,"bench":0},"shots":{"total":null,"on":null},"goals":{"total":0,"conceded":null,"assists":null,"saves":null},"passes":{"total":null,"key":null,"accuracy":null},"tackles":{"total":null,"blocks":null,"interceptions":null},"duels":{"total":null,"won":null},"dribbles":{"attempts":null,"success":null,"past":null},"fouls":{"drawn":null,"committed":null},"cards":{"yellow":0,"yellowred":0,"red":0},"penalty":{"won":null,"commited":null,"scored":null,"missed":null,"saved":null}}]},{"player":{"id":284795,"name":"A. Bellaarouch","firstname":"Alaa","lastname":"Bellaarouch","age":19,"birth":{"date":"2002-01-01","place":null,"country":"Morocco"},"nationality":"Morocco","height":null,"weight":null,"injured":false,"photo":"https://media.api-sports.io/football/players/284795.png"},"statistics":[{"team":{"id":95,"name":"Strasbourg","logo":"https://media.api-sports.io/football/teams/95.png"},"league":{"id":61,"name":"Ligue 1","country":"France","logo":"https://media.api-sports.io/football/leagues/61.png","flag":"https://media.api-sports.io/flags/fr.svg","season":2021},"games":{"appearences":0,"lineups":0,"minutes":0,"number":null,"position":"Goalkeeper","rating":null,"captain":false},"substitutes":{"_in":0,"_out":0,"bench":0},"shots":{"total":null,"on":null},"goals":{"total":0,"conceded":null,"assists":null,"saves":null},"passes":{"total":null,"key":null,"accuracy":null},"tackles":{"total":null,"blocks":null,"interceptions":null},"duels":{"total":null,"won":null},"dribbles":{"attempts":null,"success":null,"past":null},"fouls":{"drawn":null,"committed":null},"cards":{"yellow":0,"yellowred":0,"red":0},"penalty":{"won":null,"commited":null,"scored":null,"missed":null,"saved":null}}]},{"player":{"id":174768,"name":"A. Pierre","firstname":"Alexandre","lastname":"Pierre","age":20,"birth":{"date":"2001-02-25","place":null,"country":"France"},"nationality":"Haiti","height":null,"weight":null,"injured":false,"photo":"https://media.api-sports.io/football/players/174768.png"},"statistics":[{"team":{"id":95,"name":"Strasbourg","logo":"https://media.api-sports.io/football/teams/95.png"},"league":{"id":61,"name":"Ligue 1","country":"France","logo":"https://media.api-sports.io/football/leagues/61.png","flag":"https://media.api-sports.io/flags/fr.svg","season":2021},"games":{"appearences":0,"lineups":0,"minutes":0,"number":null,"position":"Goalkeeper","rating":null,"captain":false},"substitutes":{"_in":0,"_out":0,"bench":0},"shots":{"total":null,"on":null},"goals":{"total":0,"conceded":null,"assists":null,"saves":null},"passes":{"total":null,"key":null,"accuracy":null},"tackles":{"total":null,"blocks":null,"interceptions":null},"duels":{"total":null,"won":null},"dribbles":{"attempts":null,"success":null,"past":null},"fouls":{"drawn":null,"committed":null},"cards":{"yellow":0,"yellowred":0,"red":0},"penalty":{"won":null,"commited":null,"scored":null,"missed":null,"saved":null}}]},{"player":{"id":40445,"name":"K. Fila","firstname":"Karol","lastname":"Fila","age":23,"birth":{"date":"1998-06-13","place":"Gda\u0144sk","country":"Poland"},"nationality":"Poland","height":"180 cm","weight":"72 kg","injured":false,"photo":"https://media.api-sports.io/football/players/40445.png"},"statistics":[{"team":{"id":95,"name":"Strasbourg","logo":"https://media.api-sports.io/football/teams/95.png"},"league":{"id":61,"name":"Ligue 1","country":"France","logo":"https://media.api-sports.io/football/leagues/61.png","flag":"https://media.api-sports.io/flags/fr.svg","season":2021},"games":{"appearences":2,"lineups":2,"minutes":138,"number":null,"position":"Defender","rating":"6.600000","captain":false},"substitutes":{"_in":0,"_out":0,"bench":0},"shots":{"total":null,"on":null},"goals":{"total":0,"conceded":0,"assists":null,"saves":null},"passes":{"total":84,"key":null,"accuracy":38},"tackles":{"total":4,"blocks":1,"interceptions":null},"duels":{"total":18,"won":10},"dribbles":{"attempts":3,"success":1,"past":null},"fouls":{"drawn":4,"committed":1},"cards":{"yellow":1,"yellowred":0,"red":0},"penalty":{"won":null,"commited":null,"scored":0,"missed":0,"saved":null}}]},{"player":{"id":67953,"name":"L. Perrin","firstname":"Lucas","lastname":"Perrin","age":23,"birth":{"date":"1998-11-19","place":null,"country":"France"},"nationality":"France","height":"187 cm","weight":null,"injured":false,"photo":"https://media.api-sports.io/football/players/67953.png"},"statistics":[{"team":{"id":95,"name":"Strasbourg","logo":"https://media.api-sports.io/football/teams/95.png"},"league":{"id":61,"name":"Ligue 1","country":"France","logo":"https://media.api-sports.io/football/leagues/61.png","flag":"https://media.api-sports.io/flags/fr.svg","season":2021},"games":{"appearences":1,"lineups":1,"minutes":90,"number":null,"position":"Defender","rating":"6.000000","captain":false},"substitutes":{"_in":0,"_out":0,"bench":1},"shots":{"total":null,"on":null},"goals":{"total":0,"conceded":0,"assists":null,"saves":null},"passes":{"total":31,"key":null,"accuracy":28},"tackles":{"total":2,"blocks":null,"interceptions":3},"duels":{"total":12,"won":6},"dribbles":{"attempts":null,"success":null,"past":null},"fouls":{"drawn":2,"committed":3},"cards":{"yellow":0,"yellowred":0,"red":0},"penalty":{"won":null,"commited":null,"scored":0,"missed":0,"saved":null}}]},{"player":{"id":22244,"name":"A. Caci","firstname":"Anthony","lastname":"Caci","age":24,"birth":{"date":"1997-07-01","place":"Forbach","country":"France"},"nationality":"France","height":"184 cm","weight":"76 kg","injured":false,"photo":"https://media.api-sports.io/football/players/22244.png"},"statistics":[{"team":{"id":95,"name":"Strasbourg","logo":"https://media.api-sports.io/football/teams/95.png"},"league":{"id":61,"name":"Ligue 1","country":"France","logo":"https://media.api-sports.io/football/leagues/61.png","flag":"https://media.api-sports.io/flags/fr.svg","season":2021},"games":{"appearences":2,"lineups":1,"minutes":117,"number":null,"position":"Defender","rating":"6.450000","captain":false},"substitutes":{"_in":0,"_out":0,"bench":1},"shots":{"total":null,"on":null},"goals":{"total":0,"conceded":0,"assists":null,"saves":null},"passes":{"total":66,"key":1,"accuracy":27},"tackles":{"total":8,"blocks":null,"interceptions":1},"duels":{"total":24,"won":11},"dribbles":{"attempts":5,"success":2,"past":null},"fouls":{"drawn":null,"committed":5},"cards":{"yellow":0,"yellowred":0,"red":0},"penalty":{"won":null,"commited":null,"scored":0,"missed":0,"saved":null}}]},{"player":{"id":21633,"name":"A. Djiku","firstname":"Alexander","lastname":"Djiku","age":27,"birth":{"date":"1994-08-09","place":"Montpellier","country":"France"},"nationality":"Ghana","height":"182 cm","weight":"74 kg","injured":false,"photo":"https://media.api-sports.io/football/players/21633.png"},"statistics":[{"team":{"id":95,"name":"Strasbourg","logo":"https://media.api-sports.io/football/teams/95.png"},"league":{"id":61,"name":"Ligue 1","country":"France","logo":"https://media.api-sports.io/football/leagues/61.png","flag":"https://media.api-sports.io/flags/fr.svg","season":2021},"games":{"appearences":2,"lineups":2,"minutes":171,"number":null,"position":"Defender","rating":"6.100000","captain":false},"substitutes":{"_in":0,"_out":0,"bench":0},"shots":{"total":null,"on":null},"goals":{"total":0,"conceded":0,"assists":null,"saves":null},"passes":{"total":80,"key":null,"accuracy":34},"tackles":{"total":1,"blocks":2,"interceptions":2},"duels":{"total":9,"won":2},"dribbles":{"attempts":null,"success":null,"past":null},"fouls":{"drawn":null,"committed":5},"cards":{"yellow":2,"yellowred":1,"red":0},"penalty":{"won":null,"commited":null,"scored":0,"missed":0,"saved":null}}]},{"player":{"id":191240,"name":"M. Senaya","firstname":"Marvin","lastname":"Senaya","age":20,"birth":{"date":"2001-01-28","place":"Saint-Maurice","country":"France"},"nationality":"France","height":"179 cm","weight":"65 kg","injured":false,"photo":"https://media.api-sports.io/football/players/191240.png"},"statistics":[{"team":{"id":95,"name":"Strasbourg","logo":"https://media.api-sports.io/football/teams/95.png"},"league":{"id":61,"name":"Ligue 1","country":"France","logo":"https://media.api-sports.io/football/leagues/61.png","flag":"https://media.api-sports.io/flags/fr.svg","season":2021},"games":{"appearences":0,"lineups":0,"minutes":0,"number":null,"position":"Defender","rating":null,"captain":false},"substitutes":{"_in":0,"_out":0,"bench":2},"shots":{"total":null,"on":null},"goals":{"total":0,"conceded":0,"assists":null,"saves":null},"passes":{"total":null,"key":null,"accuracy":null},"tackles":{"total":null,"blocks":null,"interceptions":null},"duels":{"total":null,"won":null},"dribbles":{"attempts":null,"success":null,"past":null},"fouls":{"drawn":null,"committed":null},"cards":{"yellow":0,"yellowred":0,"red":0},"penalty":{"won":null,"commited":null,"scored":0,"missed":0,"saved":null}}]},{"player":{"id":103,"name":"J. Aholou","firstname":"Jean Eud\u00E8s","lastname":"Aholou","age":27,"birth":{"date":"1994-03-20","place":"Yopougnon","country":"C\u00F4te d\u0027Ivoire"},"nationality":"C\u00F4te d\u0027Ivoire","height":"186 cm","weight":"71 kg","injured":false,"photo":"https://media.api-sports.io/football/players/103.png"},"statistics":[{"team":{"id":95,"name":"Strasbourg","logo":"https://media.api-sports.io/football/teams/95.png"},"league":{"id":61,"name":"Ligue 1","country":"France","logo":"https://media.api-sports.io/football/leagues/61.png","flag":"https://media.api-sports.io/flags/fr.svg","season":2021},"games":{"appearences":2,"lineups":1,"minutes":48,"number":null,"position":"Midfielder","rating":"6.300000","captain":false},"substitutes":{"_in":0,"_out":0,"bench":1},"shots":{"total":null,"on":null},"goals":{"total":0,"conceded":0,"assists":null,"saves":null},"passes":{"total":12,"key":null,"accuracy":4},"tackles":{"total":1,"blocks":null,"interceptions":1},"duels":{"total":6,"won":1},"dribbles":{"attempts":null,"success":null,"past":null},"fouls":{"drawn":null,"committed":2},"cards":{"yellow":0,"yellowred":0,"red":0},"penalty":{"won":null,"commited":null,"scored":0,"missed":0,"saved":null}}]},{"player":{"id":22261,"name":"A. Thomasson","firstname":"Adrien","lastname":"Thomasson","age":28,"birth":{"date":"1993-12-10","place":"Bourg-Saint-Maurice","country":"France"},"nationality":"France","height":"177 cm","weight":"72 kg","injured":false,"photo":"https://media.api-sports.io/football/players/22261.png"},"statistics":[{"team":{"id":95,"name":"Strasbourg","logo":"https://media.api-sports.io/football/teams/95.png"},"league":{"id":61,"name":"Ligue 1","country":"France","logo":"https://media.api-sports.io/football/leagues/61.png","flag":"https://media.api-sports.io/flags/fr.svg","season":2021},"games":{"appearences":2,"lineups":1,"minutes":138,"number":null,"position":"Midfielder","rating":"6.450000","captain":false},"substitutes":{"_in":0,"_out":0,"bench":1},"shots":{"total":1,"on":null},"goals":{"total":0,"conceded":0,"assists":1,"saves":null},"passes":{"total":73,"key":1,"accuracy":28},"tackles":{"total":4,"blocks":null,"interceptions":null},"duels":{"total":19,"won":6},"dribbles":{"attempts":5,"success":null,"past":null},"fouls":{"drawn":1,"committed":4},"cards":{"yellow":0,"yellowred":0,"red":0},"penalty":{"won":null,"commited":null,"scored":0,"missed":0,"saved":null}}]},{"player":{"id":22257,"name":"D. Li\u00E9nard","firstname":"Dimitri","lastname":"Li\u00E9nard","age":33,"birth":{"date":"1988-02-13","place":"Belfort","country":"France"},"nationality":"France","height":"184 cm","weight":"77 kg","injured":false,"photo":"https://media.api-sports.io/football/players/22257.png"},"statistics":[{"team":{"id":95,"name":"Strasbourg","logo":"https://media.api-sports.io/football/teams/95.png"},"league":{"id":61,"name":"Ligue 1","country":"France","logo":"https://media.api-sports.io/football/leagues/61.png","flag":"https://media.api-sports.io/flags/fr.svg","season":2021},"games":{"appearences":2,"lineups":2,"minutes":180,"number":null,"position":"Midfielder","rating":"6.600000","captain":false},"substitutes":{"_in":0,"_out":0,"bench":0},"shots":{"total":null,"on":null},"goals":{"total":0,"conceded":0,"assists":1,"saves":null},"passes":{"total":115,"key":1,"accuracy":44},"tackles":{"total":10,"blocks":null,"interceptions":2},"duels":{"total":29,"won":17},"dribbles":{"attempts":null,"success":null,"past":null},"fouls":{"drawn":5,"committed":7},"cards":{"yellow":1,"yellowred":0,"red":0},"penalty":{"won":null,"commited":null,"scored":0,"missed":0,"saved":null}}]},{"player":{"id":22259,"name":"S. Prci\u0107","firstname":"Sanjin","lastname":"Prci\u0107","age":28,"birth":{"date":"1993-11-20","place":"Belfort","country":"France"},"nationality":"Bosnia and Herzegovina","height":"181 cm","weight":"73 kg","injured":false,"photo":"https://media.api-sports.io/football/players/22259.png"},"statistics":[{"team":{"id":95,"name":"Strasbourg","logo":"https://media.api-sports.io/football/teams/95.png"},"league":{"id":61,"name":"Ligue 1","country":"France","logo":"https://media.api-sports.io/football/leagues/61.png","flag":"https://media.api-sports.io/flags/fr.svg","season":2021},"games":{"appearences":1,"lineups":1,"minutes":76,"number":null,"position":"Midfielder","rating":"6.700000","captain":false},"substitutes":{"_in":0,"_out":0,"bench":1},"shots":{"total":1,"on":null},"goals":{"total":0,"conceded":0,"assists":null,"saves":null},"passes":{"total":51,"key":1,"accuracy":44},"tackles":{"total":null,"blocks":null,"interceptions":1},"duels":{"total":2,"won":1},"dribbles":{"attempts":null,"success":null,"past":null},"fouls":{"drawn":null,"committed":null},"cards":{"yellow":0,"yellowred":0,"red":0},"penalty":{"won":null,"commited":null,"scored":0,"missed":0,"saved":null}}]},{"player":{"id":20665,"name":"J. Bellegarde","firstname":"Jean-Ricner","lastname":"Bellegarde","age":23,"birth":{"date":"1998-06-27","place":"Colombes","country":"France"},"nationality":"France","height":"170 cm","weight":"66 kg","injured":false,"photo":"https://media.api-sports.io/football/players/20665.png"},"statistics":[{"team":{"id":95,"name":"Strasbourg","logo":"https://media.api-sports.io/football/teams/95.png"},"league":{"id":61,"name":"Ligue 1","country":"France","logo":"https://media.api-sports.io/football/leagues/61.png","flag":"https://media.api-sports.io/flags/fr.svg","season":2021},"games":{"appearences":2,"lineups":2,"minutes":174,"number":null,"position":"Midfielder","rating":"6.500000","captain":false},"substitutes":{"_in":0,"_out":0,"bench":0},"shots":{"total":1,"on":null},"goals":{"total":0,"conceded":0,"assists":null,"saves":null},"passes":{"total":87,"key":2,"accuracy":37},"tackles":{"total":2,"blocks":null,"interceptions":1},"duels":{"total":12,"won":6},"dribbles":{"attempts":1,"success":null,"past":null},"fouls":{"drawn":2,"committed":3},"cards":{"yellow":1,"yellowred":0,"red":0},"penalty":{"won":null,"commited":null,"scored":0,"missed":0,"saved":null}}]}]}