{"get":"players","parameters":{"team":"51","season":"2021"},"errors":[],"results":10,"paging":{"current":2,"total":2},"response":[{"player":{"id":48649,"name":"A. Zeqiri","firstname":"Andi Avdi","lastname":"Zeqiri","age":22,"birth":{"date":"1999-06-22","place":"Lausanne","country":"Switzerland"},"nationality":"Switzerland","height":"181 cm","weight":"72 kg","injured":false,"photo":"https://media.api-sports.io/football/players/48649.png"},"statistics":[{"team":{"id":51,"name":"Brighton","logo":"https://media.api-sports.io/football/teams/51.png"},"league":{"id":39,"name":"Premier League","country":"England","logo":"https://media.api-sports.io/football/leagues/39.png","flag":"https://media.api-sports.io/flags/gb.svg","season":2021},"games":{"appearences":0,"lineups":0,"minutes":0,"number":null,"position":"Attacker","rating":null,"captain":false},"substitutes":{"_in":0,"_out":0,"bench":1},"shots":{"total":null,"on":null},"goals":{"total":0,"conceded":0,"assists":null,"saves":null},"passes":{"total":null,"key":null,"accuracy":null},"tackles":{"total":null,"blocks":null,"interceptions":null},"duels":{"total":null,"won":null},"dribbles":{"attempts":null,"success":null,"past":null},"fouls":{"drawn":null,"committed":null},"cards":{"yellow":0,"yellowred":0,"red":0},"penalty":{"won":null,"commited":null,"scored":0,"missed":0,"saved":null}}]},{"player":{"id":18959,"name":"Robert S\u00E1nchez","firstname":"Robert","lastname":"Lynch S\u00E1nchez","age":24,"birth":{"date":"1997-11-18","place":"Cartagena","country":"Spain"},"nationality":"Spain","height":"197 cm","weight":"90 kg","injured":false,"photo":"https://media.api-sports.io/football/players/18959.png"},"statistics":[{"team":{"id":51,"name":"Brighton","logo":"https://media.api-sports.io/football/teams/51.png"},"league":{"id":39,"name":"Premier League","country":"England","logo":"https://media.api-sports.io/football/leagues/39.png","flag":"https://media.api-sports.io/flags/gb.svg","season":2021},"games":{"appearences":1,"lineups":1,"minutes":90,"number":null,"position":"Goalkeeper","rating":"6.900000","captain":false},"substitutes":{"_in":0,"_out":0,"bench":0},"shots":{"total":null,"on":null},"goals":{"total":0,"conceded":1,"assists":null,"saves":2},"passes":{"total":48,"key":1,"accuracy":27},"tackles":{"total":null,"blocks":null,"interceptions":null},"duels":{"total":2,"won":2},"dribbles":{"attempts":null,"success":null,"past":null},"fouls":{"drawn":1,"committed":null},"cards":{"yellow":0,"yellowred":0,"red":0},"penalty":{"won":null,"commited":null,"scored":0,"missed":0,"saved":0}}]},{"player":{"id":18960,"name":"J. Steele","firstname":"Jason","lastname":"Steele","age":31,"birth":{"date":"1990-08-18","place":"Newton Aycliffe","country":"England"},"nationality":"England","height":"188 cm","weight":"79 kg","injured":false,"photo":"https://media.api-sports.io/football/players/18960.png"},"statistics":[{"team":{"id":51,"name":"Brighton","logo":"https://media.api-sports.io/football/teams/51.png"},"league":{"id":39,"name":"Premier League","country":"England","logo":"https://media.api-sports.io/football/leagues/39.png","flag":"https://media.api-sports.io/flags/gb.svg","season":2021},"games":{"appearences":0,"lineups":0,"minutes":0,"number":null,"position":"Goalkeeper","rating":null,"captain":false},"substitutes":{"_in":0,"_out":0,"bench":1},"shots":{"total":null,"on":null},"goals":{"total":0,"conceded":0,"assists":null,"saves":null},"passes":{"total":null,"key":null,"accuracy":null},"tackles":{"total":null,"blocks":null,"interceptions":null},"duels":{"total":null,"won":null},"dribbles":{"attempts":null,"success":null,"past":null},"fouls":{"drawn":null,"committed":null},"cards":{"yellow":0,"yellowred":0,"red":0},"penalty":{"won":null,"commited":null,"scored":0,"missed":0,"saved":0}}]},{"player":{"id":19541,"name":"C. Walton","firstname":"Christian","lastname":"Walton","age":26,"birth":{"date":"1995-11-09","place":"Truro","country":"England"},"nationality":"England","height":"196 cm","weight":"75 kg","injured":false,"photo":"https://media.api-sports.io/football/players/19541.png"},"statistics":[{"team":{"id":51,"name":"Brighton","logo":"https://media.api-sports.io/football/teams/51.png"},"league":{"id":39,"name":"Premier League","country":"England","logo":"https://media.api-sports.io/football/leagues/39.png","flag":"https://media.api-sports.io/flags/gb.svg","season":2021},"games":{"appearences":0,"lineups":0,"minutes":0,"number":null,"position":"Goalkeeper","rating":null,"captain":false},"substitutes":{"_in":0,"_out":0,"bench":0},"shots":{"total":null,"on":null},"goals":{"total":0,"conceded":null,"assists":null,"saves":null},"passes":{"total":null,"key":null,"accuracy":null},"tackles":{"total":null,"blocks":null,"interceptions":null},"duels":{"total":null,"won":null},"dribbles":{"attempts":null,"success":null,"past":null},"fouls":{"drawn":null,"committed":null},"cards":{"yellow":0,"yellowred":0,"red":0},"penalty":{"won":null,"commited":null,"scored":null,"missed":null,"saved":null}}]},{"player":{"id":125618,"name":"M. Karbownik","firstname":"Micha\u0142","lastname":"Karbownik","age":20,"birth":{"date":"2001-03-13","place":"Radom","country":"Poland"},"nationality":"Poland","height":"175 cm","weight":null,"injured":false,"photo":"https://media.api-sports.io/football/players/125618.png"},"statistics":[{"team":{"id":51,"name":"Brighton","logo":"https://media.api-sports.io/football/teams/51.png"},"league":{"id":39,"name":"Premier League","country":"England","logo":"https://media.api-sports.io/football/leagues/39.png","flag":"https://media.api-sports.io/flags/gb.svg","season":2021},"games":{"appearences":0,"lineups":0,"minutes":0,"number":null,"position":"Defender","rating":null,"captain":false},"substitutes":{"_in":0,"_out":0,"bench":1},"shots":{"total":null,"on":null},"goals":{"total":0,"conceded":0,"assists":null,"saves":null},"passes":{"total":null,"key":null,"accuracy":null},"tackles":{"total":null,"blocks":null,"interceptions":null},"duels":{"total":null,"won":null},"dribbles":{"attempts":null,"success":null,"past":null},"fouls":{"drawn":null,"committed":null},"cards":{"yellow":0,"yellowred":0,"red":0},"penalty":{"won":null,"commited":null,"scored":0,"missed":0,"saved":null}}]},{"player":{"id":116117,"name":"M. Caicedo","firstname":"Mois\u00E9s Isaac","lastname":"Caicedo Corozo","age":20,"birth":{"date":"2001-11-02","place":"Santo Domingo","country":"Ecuador"},"nationality":"Ecuador","height":"178 cm","weight":"73 kg","injured":false,"photo":"https://media.api-sports.io/football/players/116117.png"},"statistics":[{"team":{"id":51,"name":"Brighton","logo":"https://media.api-sports.io/football/teams/51.png"},"league":{"id":39,"name":"Premier League","country":"England","logo":"https://media.api-sports.io/football/leagues/39.png","flag":"https://media.api-sports.io/flags/gb.svg","season":2021},"games":{"appearences":0,"lineups":0,"minutes":0,"number":null,"position":"Midfielder","rating":null,"captain":false},"substitutes":{"_in":0,"_out":0,"bench":1},"shots":{"total":null,"on":null},"goals":{"total":0,"conceded":0,"assists":null,"saves":null},"passes":{"total":null,"key":null,"accuracy":null},"tackles":{"total":null,"blocks":null,"interceptions":null},"duels":{"total":null,"won":null},"dribbles":{"attempts":null,"success":null,"past":null},"fouls":{"drawn":null,"committed":null},"cards":{"yellow":0,"yellowred":0,"red":0},"penalty":{"won":null,"commited":null,"scored":0,"missed":0,"saved":null}}]},{"player":{"id":18973,"name":"S. March","firstname":"Solomon","lastname":"March","age":27,"birth":{"date":"1994-07-20","place":"Eastbourne","country":"England"},"nationality":"England","height":"180 cm","weight":"88 kg","injured":false,"photo":"https://media.api-sports.io/football/players/18973.png"},"statistics":[{"team":{"id":51,"name":"Brighton","logo":"https://media.api-sports.io/football/teams/51.png"},"league":{"id":39,"name":"Premier League","country":"England","logo":"https://media.api-sports.io/football/leagues/39.png","flag":"https://media.api-sports.io/flags/gb.svg","season":2021},"games":{"appearences":1,"lineups":1,"minutes":90,"number":null,"position":"Midfielder","rating":"7.300000","captain":false},"substitutes":{"_in":0,"_out":0,"bench":0},"shots":{"total":1,"on":1},"goals":{"total":0,"conceded":0,"assists":null,"saves":null},"passes":{"total":35,"key":3,"accuracy":30},"tackles":{"total":3,"blocks":null,"interceptions":null},"duels":{"total":9,"won":5},"dribbles":{"attempts":null,"success":null,"past":null},"fouls":{"drawn":2,"committed":1},"cards":{"yellow":0,"yellowred":0,"red":0},"penalty":{"won":null,"commited":null,"scored":0,"missed":0,"saved":null}}]},{"player":{"id":17715,"name":"S. Alzate","firstname":"Steven","lastname":"Alzate","age":23,"birth":{"date":"1998-09-08","place":"London","country":"England"},"nationality":"Colombia","height":"180 cm","weight":null,"injured":false,"photo":"https://media.api-sports.io/football/players/17715.png"},"statistics":[{"team":{"id":51,"name":"Brighton","logo":"https://media.api-sports.io/football/teams/51.png"},"league":{"id":39,"name":"Premier League","country":"England","logo":"https://media.api-sports.io/football/leagues/39.png","flag":"https://media.api-sports.io/flags/gb.svg","season":2021},"games":{"appearences":1,"lineups":1,"minutes":72,"number":null,"position":"Attacker","rating":"6.900000","captain":false},"substitutes":{"_in":0,"_out":0,"bench":0},"shots":{"total":null,"on":null},"goals":{"total":0,"conceded":0,"assists":null,"saves":null},"passes":{"total":38,"key":2,"accuracy":36},"tackles":{"total":2,"blocks":null,"interceptions":null},"duels":{"total":9,"won":4},"dribbles":{"attempts":null,"success":null,"past":null},"fouls":{"drawn":1,"committed":2},"cards":{"yellow":0,"yellowred":0,"red":0},"penalty":{"won":null,"commited":null,"scored":0,"missed":0,"saved":null}}]},{"player":{"id":18978,"name":"F. Andone","firstname":"Florin","lastname":"Andone","age":28,"birth":{"date":"1993-04-11","place":"Boto\u0219ani","country":"Romania"},"nationality":"Romania","height":"180 cm","weight":"78 kg","injured":false,"photo":"https://media.api-sports.io/football/players/18978.png"},"statistics":[{"team":{"id":51,"name":"Brighton","logo":"https://media.api-sports.io/football/teams/51.png"},"league":{"id":39,"name":"Premier League","country":"England","logo":"https://media.api-sports.io/football/leagues/39.png","flag":"https://media.api-sports.io/flags/gb.svg","season":2021},"games":{"appearences":0,"lineups":0,"minutes":0,"number":null,"position":"Attacker","rating":null,"captain":false},"substitutes":{"_in":0,"_out":0,"bench":1},"shots":{"total":null,"on":null},"goals":{"total":0,"conceded":0,"assists":null,"saves":null},"passes":{"total":null,"key":null,"accuracy":null},"tackles":{"total":null,"blocks":null,"interceptions":null},"duels":{"total":null,"won":null},"dribbles":{"attempts":null,"success":null,"past":null},"fouls":{"drawn":null,"committed":null},"cards":{"yellow":0,"yellowred":0,"red":0},"penalty":{"won":null,"commited":null,"scored":0,"missed":0,"saved":null}}]},{"player":{"id":19772,"name":"A. Connolly","firstname":"Aaron Anthony","lastname":"Connolly","age":21,"birth":{"date":"2000-01-28","place":"Galway","country":"Republic of Ireland"},"nationality":"Republic of Ireland","height":null,"weight":null,"injured":false,"photo":"https://media.api-sports.io/football/players/19772.png"},"statistics":[{"team":{"id":51,"name":"Brighton","logo":"https://media.api-sports.io/football/teams/51.png"},"league":{"id":39,"name":"Premier League","country":"England","logo":"https://media.api-sports.io/football/leagues/39.png","flag":"https://media.api-sports.io/flags/gb.svg","season":2021},"games":{"appearences":0,"lineups":0,"minutes":0,"number":null,"position":"Attacker","rating":null,"captain":false},"substitutes":{"_in":0,"_out":0,"bench":0},"shots":{"total":null,"on":null},"goals":{"total":0,"conceded":null,"assists":null,"saves":null},"passes":{"total":null,"key":null,"accuracy":null},"tackles":{"total":null,"blocks":null,"interceptions":null},"duels":{"total":null,"won":null},"dribbles":{"attempts":null,"success":null,"past":null},"fouls":{"drawn":null,"committed":null},"cards":{"yellow":0,"yellowred":0,"red":0},"penalty":{"won":null,"commited":null,"scored":null,"missed":null,"saved":null}}]}]}